{
    "module_map": "AudioSdkTob.modulemap",
    "preserve_paths": [
        "**/*.bwp"
    ],
    "osx": {
        "header_mappings_dir": "inc",
        "vendored_libraries": [
            "lib/libbdaudioeffect.a",
            "ios-arch-osx/*_AudioSdkTob_*awesome_*.a"
        ],
        "source_files": "inc/**/*.{h,hh,hpp,tpp}"
    },
    "name": "AudioSdkTob",
    "license": {
        "type": "Copyright",
        "text": "Bytedance copyright"
    },
    "platforms": {
        "osx": "10.11",
        "ios": "8.0"
    },
    "prepare_command": "",
    "source_files": [
        "AudioSdkTob-bitdummy.m"
    ],
    "ios": {
        "header_mappings_dir": "inc",
        "frameworks": [
            "Accelerate",
            "AudioToolbox",
            "CoreFoundation",
            "UIKit",
            "Foundation",
            "JavaScriptCore"
        ],
        "vendored_libraries": [
            "lib/libbdaudioeffect.a",
            "ios-arch-iphone/*_AudioSdkTob_*awesome_*.a"
        ],
        "source_files": "inc/**/*.{h,hh,hpp,tpp}"
    },
    "summary": "framework_summary",
    "libraries": "c++",
    "source": {
        "http": "https://hstob-cdn-tos.volccdn.com/volcengine/AudioSdkTob/5.0.1-tobve/AudioSdkTob.framework.tar.xz"
    },
    "version": "5.0.1-tobve",
    "frameworks": [
        "Accelerate",
        "AudioToolbox",
        "CoreFoundation"
    ],
    "authors": {
        "zhuxiangning.zxn": "zhuxiangning.zxn@bytedance.com"
    },
    "static_framework": true,
    "homepage": "https://github.com/volcengine/volcengine-specs",
    "repoId": "36675",
    "description": "framework_description"
}