{"name": "VEKit", "version": "22.7.11", "summary": "A short description of VEKit.", "description": "TODO: Add long description of the pod here.", "homepage": "https://github.com/volcengine/volcengine-specs", "license": {"type": "MIT", "file": "LICENSE"}, "authors": {"shangguanchengyang": "shangguanchengyang.1@bytedance.com"}, "source": {"git": "https://gitee.com/volcengine/VEKit.git"}, "platforms": {"ios": "9.0"}, "static_framework": true, "source_files": "**/*.{h,m,mm}", "public_header_files": "**/*.h", "default_subspecs": ["OneKit"], "subspecs": [{"name": "OneKit", "dependencies": {"OneKit": ["1.3.10"]}}, {"name": "VEH5Kit", "dependencies": {"VEH5Kit": ["1.1.6"]}}, {"name": "VEAppUpdateHelper", "dependencies": {"VEAppUpdateHelper": ["1.0.19"]}}, {"name": "VEInstall", "dependencies": {"VEInstall": ["1.0.3"]}}, {"name": "VERemoteConfig", "dependencies": {"VERemoteConfig": ["1.0.4"]}}, {"name": "RangersAppLog", "dependencies": {"RangersAppLog": ["6.9.0"]}}, {"name": "RangersAPM", "dependencies": {"RangersAPM/Crash": ["2.9.0"]}}, {"name": "RARegisterKit", "dependencies": {"RARegisterKit": ["0.0.4"]}}, {"name": "BDHotfix", "dependencies": {"BDHotfix": ["1.0.14"]}}, {"name": "TTNetworkManager", "dependencies": {"TTNetworkManager": ["5.0.29.26"]}}, {"name": "SwiftOneKit", "dependencies": {"SwiftOneKit": ["1.0.1"]}}, {"name": "Timor", "dependencies": {"Timor": ["2.3.2.1"]}}, {"name": "TimorHostPlugins", "dependencies": {"TimorHostPlugins": ["2.3.2.1"]}}, {"name": "VESMStorage", "dependencies": {"VESMStorage": ["0.0.4"]}}, {"name": "VESafeKeyboard", "dependencies": {"VESafeKeyboard": ["1.0.1"]}}, {"name": "VECampaign", "dependencies": {"VECampaign": ["0.0.1"]}}, {"name": "VESDKMonitorWrapper", "dependencies": {"VESDKMonitorWrapper": ["0.0.2"]}}, {"name": "VEShare", "dependencies": {"VEShare": ["0.0.9"]}}]}